scgraph/__init__.py
scgraph/cache.py
scgraph/core.py
scgraph/geograph.py
scgraph/graph.py
scgraph/grid.py
scgraph/spanning.py
scgraph/utils.py
scgraph/bmssp/__init__.py
scgraph/bmssp/bmssp_data_structure.py
scgraph/bmssp/bmssp_solver.py
scgraph/geographs/__init__.py
scgraph/geographs/marnet.py
scgraph/geographs/north_america_rail.py
scgraph/geographs/oak_ridge_maritime.py
scgraph/geographs/us_freeway.py
scgraph/helpers/__init__.py
scgraph/helpers/geojson.py
scgraph/helpers/kd_tree.py
scgraph/helpers/shape_mover_utils.py
scgraph/helpers/visvalingam.py
scgraph/helpers/xyz.py
scgraph-2.14.1.dist-info/licenses/LICENSE
scgraph-2.14.1.dist-info/METADATA
scgraph-2.14.1.dist-info/WHEEL
scgraph-2.14.1.dist-info/top_level.txt
scgraph-2.14.1.dist-info/RECORD
