Metadata-Version: 2.4
Name: scgraph
Version: 2.14.1
Summary: Determine an approximate route between two points on earth.
Author-email: Connor Makowski <conmak@mit.edu>
Project-URL: Homepage, https://github.com/connor-makowski/scgraph
Project-URL: Bug Tracker, https://github.com/connor-makowski/scgraph/issues
Project-URL: Documentation, https://connor-makowski.github.io/scgraph/scgraph.html
Classifier: Programming Language :: Python :: 3
Classifier: License :: OSI Approved :: MIT License
Classifier: Operating System :: OS Independent
Requires-Python: >=3.10
License-File: LICENSE
Dynamic: license-file
